gbv/CookiesCache.py
gbv/FavoriteCrawling.py
gbv/GenerateHeaders.py
gbv/GetBilibiliCookies.py
gbv/GetBilibiliVideo.py
gbv/bvid_aid.py
gbv/gbv.py
gbv/methods.py
gbv/requirements.py
gbv/terminal.py
gbv-0.1.2.dist-info/METADATA
gbv-0.1.2.dist-info/WHEEL
gbv-0.1.2.dist-info/entry_points.txt
gbv-0.1.2.dist-info/top_level.txt
gbv-0.1.2.dist-info/RECORD
