Metadata-Version: 2.1
Name: gbv
Version: 0.1.2
Summary: A package to get videos from Bilibili
Home-page: https://github.com/PYmili/gbv
Author: PYmili
Author-email: mc2005wj@163.com
Classifier: Programming Language :: Python :: 3
Classifier: License :: OSI Approved :: GNU General Public License v3 (GPLv3)
Classifier: Operating System :: OS Independent
Requires-Python: >=3.9
Requires-Dist: beautifulsoup4
Requires-Dist: bs4
Requires-Dist: certifi
Requires-Dist: charset-normalizer
Requires-Dist: colorama
Requires-Dist: fileid
Requires-Dist: idna
Requires-Dist: loguru
Requires-Dist: lxml
Requires-Dist: requests
Requires-Dist: rookiepy
Requires-Dist: setuptools
Requires-Dist: soupsieve
Requires-Dist: tqdm
Requires-Dist: urllib3
Requires-Dist: uuid
Requires-Dist: win32-setctime
